bbc.py
bbcindicators-0.0.1.dist-info/METADATA
bbcindicators-0.0.1.dist-info/WHEEL
bbcindicators-0.0.1.dist-info/top_level.txt
bbcindicators-0.0.1.dist-info/RECORD
