Metadata-Version: 2.1
Name: bbcindicators
Version: 0.0.1
Summary: BBC indicator and custom functions
Author: Balaji Betadur
Classifier: Programming Language :: Python :: 3
Classifier: License :: OSI Approved :: MIT License
Classifier: Operating System :: OS Independent
Requires-Python: >=3.6
